odoo/addons/stock_available_to_promise_release/README.rst
odoo/addons/stock_available_to_promise_release/__init__.py
odoo/addons/stock_available_to_promise_release/__manifest__.py
odoo/addons/stock_available_to_promise_release/i18n/es_AR.po
odoo/addons/stock_available_to_promise_release/i18n/it.po
odoo/addons/stock_available_to_promise_release/i18n/stock_available_to_promise_release.pot
odoo/addons/stock_available_to_promise_release/migrations/14.0.2.0.0/post-migrate.py
odoo/addons/stock_available_to_promise_release/migrations/14.0.2.5.0/post-migrate.py
odoo/addons/stock_available_to_promise_release/models/__init__.py
odoo/addons/stock_available_to_promise_release/models/product_product.py
odoo/addons/stock_available_to_promise_release/models/res_company.py
odoo/addons/stock_available_to_promise_release/models/res_config_settings.py
odoo/addons/stock_available_to_promise_release/models/stock_location.py
odoo/addons/stock_available_to_promise_release/models/stock_location_route.py
odoo/addons/stock_available_to_promise_release/models/stock_move.py
odoo/addons/stock_available_to_promise_release/models/stock_picking.py
odoo/addons/stock_available_to_promise_release/models/stock_picking_type.py
odoo/addons/stock_available_to_promise_release/models/stock_rule.py
odoo/addons/stock_available_to_promise_release/readme/CONFIGURE.rst
odoo/addons/stock_available_to_promise_release/readme/CONTRIBUTORS.rst
odoo/addons/stock_available_to_promise_release/readme/CREDITS.rst
odoo/addons/stock_available_to_promise_release/readme/DESCRIPTION.rst
odoo/addons/stock_available_to_promise_release/readme/USAGE.rst
odoo/addons/stock_available_to_promise_release/security/ir.model.access.csv
odoo/addons/stock_available_to_promise_release/static/description/icon.png
odoo/addons/stock_available_to_promise_release/static/description/index.html
odoo/addons/stock_available_to_promise_release/tests/__init__.py
odoo/addons/stock_available_to_promise_release/tests/common.py
odoo14_addon_stock_available_to_promise_release-14.0.3.3.2.dist-info/METADATA
odoo14_addon_stock_available_to_promise_release-14.0.3.3.2.dist-info/WHEEL
odoo14_addon_stock_available_to_promise_release-14.0.3.3.2.dist-info/top_level.txt
odoo14_addon_stock_available_to_promise_release-14.0.3.3.2.dist-info/RECORD
